robot_properties_fingers/__init__.py
robot_properties_fingers/pinocchio_utils.py
robot_properties_fingers/meshes/BL-M_Table_ASM_big.stl
robot_properties_fingers/meshes/BL-M_Table_ASM_small.stl
robot_properties_fingers/meshes/BL_Finger_Holder_SIM.stl
robot_properties_fingers/meshes/SIM_BL_FINGER_TIP_LINK.stl
robot_properties_fingers/meshes/SIM__BL-Finger_Base.stl
robot_properties_fingers/meshes/SIM__BL-Finger_Intermediate.stl
robot_properties_fingers/meshes/SIM__BL-Finger_Proximal.stl
robot_properties_fingers/meshes/Stage_simplified.stl
robot_properties_fingers/meshes/Tip_link_Modular_SIM.stl
robot_properties_fingers/meshes/finger_padding.stl
robot_properties_fingers/meshes/high_table_boundary.stl
robot_properties_fingers/meshes/object_containment_sim.stl
robot_properties_fingers/meshes/trifinger_table_without_border.stl
robot_properties_fingers/meshes/edu/base_back.stl
robot_properties_fingers/meshes/edu/base_front.stl
robot_properties_fingers/meshes/edu/base_side_left.stl
robot_properties_fingers/meshes/edu/base_side_right.stl
robot_properties_fingers/meshes/edu/base_top.stl
robot_properties_fingers/meshes/edu/frame_wall.stl
robot_properties_fingers/meshes/edu/lower_link.stl
robot_properties_fingers/meshes/edu/middle_link.stl
robot_properties_fingers/meshes/edu/upper_link.stl
robot_properties_fingers/meshes/pro/center_axis_sim.stl
robot_properties_fingers/meshes/pro/int_sim.stl
robot_properties_fingers/meshes/pro/motor_sim.stl
robot_properties_fingers/meshes/pro/prox-sim.stl
robot_properties_fingers/meshes/pro/tip_link_sim.stl
robot_properties_fingers/meshes/pro/tip_sim.stl
robot_properties_fingers/meshes/pro/detailed/SIM__BL-Finger_Base.stl
robot_properties_fingers/meshes/pro/detailed/SIM__BL-Finger_Center.stl
robot_properties_fingers/meshes/pro/detailed/SIM__BL-Finger_Intermediate.stl
robot_properties_fingers/meshes/pro/detailed/SIM__BL-Finger_Motor.stl
robot_properties_fingers/meshes/pro/detailed/SIM__BL-Finger_Proximal.stl
robot_properties_fingers-2.0.2.dist-info/LICENSE
robot_properties_fingers-2.0.2.dist-info/METADATA
robot_properties_fingers-2.0.2.dist-info/WHEEL
robot_properties_fingers-2.0.2.dist-info/top_level.txt
robot_properties_fingers-2.0.2.dist-info/zip-safe
robot_properties_fingers-2.0.2.dist-info/RECORD
