Metadata-Version: 2.1
Name: robot_properties_fingers
Version: 2.0.2
Summary: URDF files and meshes of the (Tri-)Finger robots.
Home-page: https://open-dynamic-robot-initiative.github.io/robot_properties_fingers/
Maintainer: Felix Kloss
Maintainer-email: felix.kloss@tue.mpg.de
License: BSD-3-Clause
Classifier: Development Status :: 5 - Production/Stable
Classifier: License :: OSI Approved :: BSD License
Classifier: Programming Language :: Python :: 3
Classifier: Topic :: Scientific/Engineering
License-File: LICENSE
Requires-Dist: xacro
Requires-Dist: pin
Provides-Extra: test
Requires-Dist: pytest ; extra == 'test'
